pyNastran/__init__.py
pyNastran/all_tests.py
pyNastran/all_tests_no_gui.py
pyNastran/nptyping_interface.py
pyNastran/version.py
pyNastran/bdf/__init__.py
pyNastran/bdf/bdf.py
pyNastran/bdf/bdf_methods.py
pyNastran/bdf/case_control_deck.py
pyNastran/bdf/errors.py
pyNastran/bdf/field_writer.py
pyNastran/bdf/field_writer_16.py
pyNastran/bdf/field_writer_8.py
pyNastran/bdf/field_writer_double.py
pyNastran/bdf/subcase.py
pyNastran/bdf/utils.py
pyNastran/bdf/write_path.py
pyNastran/bdf/bdf_interface/__init__.py
pyNastran/bdf/bdf_interface/add_card.py
pyNastran/bdf/bdf_interface/add_methods.py
pyNastran/bdf/bdf_interface/assign_type.py
pyNastran/bdf/bdf_interface/assign_type_force.py
pyNastran/bdf/bdf_interface/attributes.py
pyNastran/bdf/bdf_interface/bdf_card.py
pyNastran/bdf/bdf_interface/card_groups.py
pyNastran/bdf/bdf_interface/case_control_cards.py
pyNastran/bdf/bdf_interface/compare_card_content.py
pyNastran/bdf/bdf_interface/cross_reference.py
pyNastran/bdf/bdf_interface/encoding.py
pyNastran/bdf/bdf_interface/get_card.py
pyNastran/bdf/bdf_interface/get_methods.py
pyNastran/bdf/bdf_interface/hdf5_exporter.py
pyNastran/bdf/bdf_interface/hdf5_loader.py
pyNastran/bdf/bdf_interface/include_file.py
pyNastran/bdf/bdf_interface/model_group.py
pyNastran/bdf/bdf_interface/pybdf.py
pyNastran/bdf/bdf_interface/replication.py
pyNastran/bdf/bdf_interface/safe_cross_reference.py
pyNastran/bdf/bdf_interface/stats.py
pyNastran/bdf/bdf_interface/uncross_reference.py
pyNastran/bdf/bdf_interface/utils.py
pyNastran/bdf/bdf_interface/verify_validate.py
pyNastran/bdf/bdf_interface/write_mesh.py
pyNastran/bdf/bdf_interface/write_mesh_file.py
pyNastran/bdf/bdf_interface/write_mesh_utils.py
pyNastran/bdf/bdf_interface/subcase/__init__.py
pyNastran/bdf/bdf_interface/subcase/cards.py
pyNastran/bdf/bdf_interface/subcase/cards_check.py
pyNastran/bdf/bdf_interface/subcase/cards_int.py
pyNastran/bdf/bdf_interface/subcase/cards_str.py
pyNastran/bdf/bdf_interface/subcase/h5py_interface.py
pyNastran-1.4.0.dist-info/LICENSE.md
pyNastran-1.4.0.dist-info/METADATA
pyNastran-1.4.0.dist-info/WHEEL
pyNastran-1.4.0.dist-info/entry_points.txt
pyNastran-1.4.0.dist-info/top_level.txt
pyNastran-1.4.0.dist-info/RECORD
