Metadata-Version: 2.1
Name: pyNastran
Version: 1.4.0
Summary: Nastran BDF/F06/OP2/OP4 File reader/editor/writer/viewer
Author: Steve Doyle
License: Copyright (c) 2011-2024 Steven Doyle.
Project-URL: homepage, https://github.com/SteveDoyle2/pyNastran/
Project-URL: issue_tracker, https://github.com/SteveDoyle2/pyNastran/issues
Project-URL: documentation, https://pynastran-git.readthedocs.io/en/latest/
Project-URL: repository, https://github.com/SteveDoyle2/pyNastran.git
Keywords: nastran
Classifier: Topic :: Software Development
Classifier: Topic :: Software Development :: Libraries :: Python Modules
Classifier: Topic :: Scientific/Engineering
Classifier: Topic :: Scientific/Engineering :: Visualization
Classifier: Intended Audience :: Science/Research
Classifier: Intended Audience :: Developers
Classifier: Operating System :: OS Independent
Classifier: Programming Language :: Python
Classifier: Programming Language :: Python :: 3 :: Only
Classifier: Programming Language :: Python :: 3
Classifier: Programming Language :: Python :: 3.9
Classifier: Programming Language :: Python :: 3.10
Classifier: Programming Language :: Python :: 3.11
Classifier: Programming Language :: Python :: 3.12
Requires-Python: >=3.9
License-File: LICENSE.md
Requires-Dist: numpy <2
Requires-Dist: scipy <2
Requires-Dist: matplotlib
Requires-Dist: cpylog >=1.4.0
Requires-Dist: docopt-ng >=0.9.0
Requires-Dist: colorama
Provides-Extra: dev
Requires-Dist: tables ; extra == 'dev'
Requires-Dist: wheel ; extra == 'dev'
Requires-Dist: codecov ; extra == 'dev'
Provides-Extra: gui_pyqt5
Requires-Dist: pandas <3.0,>=1.0 ; extra == 'gui_pyqt5'
Requires-Dist: h5py ; extra == 'gui_pyqt5'
Requires-Dist: PyQt5 ; extra == 'gui_pyqt5'
Requires-Dist: vtk >=9.0 ; extra == 'gui_pyqt5'
Requires-Dist: qtpy ; extra == 'gui_pyqt5'
Requires-Dist: imageio <3.0 ; extra == 'gui_pyqt5'
Requires-Dist: pillow !=7.1.0,>=5.2.0 ; extra == 'gui_pyqt5'
Provides-Extra: gui_pyside2
Requires-Dist: pandas <3.0,>=1.0 ; extra == 'gui_pyside2'
Requires-Dist: h5py ; extra == 'gui_pyside2'
Requires-Dist: PySide2 ; extra == 'gui_pyside2'
Requires-Dist: vtk >=9.0 ; extra == 'gui_pyside2'
Requires-Dist: qtpy ; extra == 'gui_pyside2'
Requires-Dist: imageio <3.0 ; extra == 'gui_pyside2'
Requires-Dist: pillow !=7.1.0,>=5.2.0 ; extra == 'gui_pyside2'
Provides-Extra: nogui
Requires-Dist: pandas <3.0,>=1.0 ; extra == 'nogui'
Requires-Dist: h5py ; extra == 'nogui'
Provides-Extra: none
